fds/__init__.py
fds/sdk/__init__.py
fds/sdk/FactSetTrading/__init__.py
fds/sdk/FactSetTrading/api_client.py
fds/sdk/FactSetTrading/configuration.py
fds/sdk/FactSetTrading/exceptions.py
fds/sdk/FactSetTrading/model_utils.py
fds/sdk/FactSetTrading/rest.py
fds/sdk/FactSetTrading/api/__init__.py
fds/sdk/FactSetTrading/api/child_orders_api.py
fds/sdk/FactSetTrading/api/inbound_orders_api.py
fds/sdk/FactSetTrading/api/parent_orders_api.py
fds/sdk/FactSetTrading/apis/__init__.py
fds/sdk/FactSetTrading/model/__init__.py
fds/sdk/FactSetTrading/model/cancel_child_order.py
fds/sdk/FactSetTrading/model/cancel_child_orders.py
fds/sdk/FactSetTrading/model/cancel_child_orders_root.py
fds/sdk/FactSetTrading/model/cancel_inbound_order.py
fds/sdk/FactSetTrading/model/cancel_inbound_orders.py
fds/sdk/FactSetTrading/model/cancel_inbound_orders_root.py
fds/sdk/FactSetTrading/model/child_order.py
fds/sdk/FactSetTrading/model/child_order_info.py
fds/sdk/FactSetTrading/model/child_order_reject_info.py
fds/sdk/FactSetTrading/model/child_orders.py
fds/sdk/FactSetTrading/model/child_orders_response.py
fds/sdk/FactSetTrading/model/child_orders_response_root.py
fds/sdk/FactSetTrading/model/child_orders_root.py
fds/sdk/FactSetTrading/model/client_error_response.py
fds/sdk/FactSetTrading/model/create_child_order_info.py
fds/sdk/FactSetTrading/model/create_child_order_reject_info.py
fds/sdk/FactSetTrading/model/create_child_orders_response.py
fds/sdk/FactSetTrading/model/create_child_orders_response_root.py
fds/sdk/FactSetTrading/model/error.py
fds/sdk/FactSetTrading/model/error_source.py
fds/sdk/FactSetTrading/model/inbound_order.py
fds/sdk/FactSetTrading/model/inbound_order_metadata.py
fds/sdk/FactSetTrading/model/inbound_orders.py
fds/sdk/FactSetTrading/model/inbound_orders_response.py
fds/sdk/FactSetTrading/model/inbound_orders_response_root.py
fds/sdk/FactSetTrading/model/inbound_orders_root.py
fds/sdk/FactSetTrading/model/instrument.py
fds/sdk/FactSetTrading/model/parent_id.py
fds.sdk.FactSetTrading-0.25.2.dist-info/LICENSE
fds.sdk.FactSetTrading-0.25.2.dist-info/METADATA
fds.sdk.FactSetTrading-0.25.2.dist-info/WHEEL
fds.sdk.FactSetTrading-0.25.2.dist-info/top_level.txt
fds.sdk.FactSetTrading-0.25.2.dist-info/RECORD
